podle/__init__.py
podle/admin.py
podle/apps.py
podle/managers.py
podle/models.py
podle/podle.py
podle/serializers.py
podle/urls.py
podle/views.py
podle/management/__init__.py
podle/management/commands/__init__.py
podle/management/commands/create_or_delete_podle_rss_feeds.py
podle/migrations/0001_initial.py
podle/migrations/0002_rssfeed.py
podle/migrations/__init__.py
podle/signals/__init__.py
podle/signals/handlers.py
django_podle-0.7.0.dist-info/LICENSE
django_podle-0.7.0.dist-info/METADATA
django_podle-0.7.0.dist-info/WHEEL
django_podle-0.7.0.dist-info/top_level.txt
django_podle-0.7.0.dist-info/RECORD
