Metadata-Version: 2.1
Name: django-podle
Version: 0.7.0
Summary: Integration with Podle.io podcast app
Home-page: https://github.com/briefmnews/django-podle
Author: Brief.me
Author-email: tech@brief.me
License: MIT
Classifier: Environment :: Web Environment
Classifier: Framework :: Django
Classifier: Framework :: Django :: 3.2
Classifier: Operating System :: OS Independent
Classifier: Programming Language :: Python
Classifier: Topic :: Software Development :: Libraries :: Python Modules
Classifier: Programming Language :: Python
Classifier: Programming Language :: Python :: 3
Classifier: Programming Language :: Python :: 3.7
Classifier: Programming Language :: Python :: 3.8
Classifier: Programming Language :: Python :: 3.9
Requires-Python: >=3.7
License-File: LICENSE
Requires-Dist: Django (>=3.2)
Requires-Dist: djangorestframework (>=3)
Requires-Dist: requests (>=2)
